README.md
setup.py
ext_cloud/__init__.py
ext_cloud/test.py
ext_cloud/test_metrics.py
ext_cloud.egg-info/PKG-INFO
ext_cloud.egg-info/SOURCES.txt
ext_cloud.egg-info/dependency_links.txt
ext_cloud.egg-info/requires.txt
ext_cloud.egg-info/top_level.txt
ext_cloud/AWS/AWS.py
ext_cloud/AWS/AWSBaseCloud.py
ext_cloud/AWS/__init__.py
ext_cloud/AWS/AWSCompute/AWSCompute.py
ext_cloud/AWS/AWSCompute/AWSInstance.py
ext_cloud/AWS/AWSCompute/AWSInstanceType.py
ext_cloud/AWS/AWSCompute/AWSInstanceTypeDict.py
ext_cloud/AWS/AWSCompute/AWSKeypair.py
ext_cloud/AWS/AWSCompute/AWSSecurityGroup.py
ext_cloud/AWS/AWSCompute/AWSSecurityGroupRule.py
ext_cloud/AWS/AWSCompute/__init__.py
ext_cloud/AWS/AWSImages/AWSImage.py
ext_cloud/AWS/AWSImages/AWSImageDict.py
ext_cloud/AWS/AWSImages/AWSImages.py
ext_cloud/AWS/AWSImages/__init__.py
ext_cloud/AWS/AWSNetworks/AWSGateway.py
ext_cloud/AWS/AWSNetworks/AWSNetwork.py
ext_cloud/AWS/AWSNetworks/AWSNetworks.py
ext_cloud/AWS/AWSNetworks/AWSRouter.py
ext_cloud/AWS/AWSNetworks/AWSSubnet.py
ext_cloud/AWS/AWSNetworks/__init__.py
ext_cloud/AWS/AWSObjectStore/AWSBucket.py
ext_cloud/AWS/AWSObjectStore/AWSKey.py
ext_cloud/AWS/AWSObjectStore/AWSObjectStore.py
ext_cloud/AWS/AWSObjectStore/__init__.py
ext_cloud/AWS/AWSRegions/AWSRegion.py
ext_cloud/AWS/AWSRegions/AWSRegions.py
ext_cloud/AWS/AWSRegions/AWSZone.py
ext_cloud/AWS/AWSRegions/__init__.py
ext_cloud/AWS/AWSTemplates/AWSTemplate.py
ext_cloud/AWS/AWSTemplates/AWSTemplates.py
ext_cloud/AWS/AWSTemplates/__init__.py
ext_cloud/AWS/AWSVolumes/AWSSnapshot.py
ext_cloud/AWS/AWSVolumes/AWSVolume.py
ext_cloud/AWS/AWSVolumes/AWSVolumes.py
ext_cloud/AWS/AWSVolumes/__init__.py
ext_cloud/Azure/Azure.py
ext_cloud/Azure/AzureBaseCloud.py
ext_cloud/Azure/__init__.py
ext_cloud/Azure/AzureCompute/AzureCompute.py
ext_cloud/Azure/AzureCompute/AzureInstance.py
ext_cloud/Azure/AzureCompute/AzureInstanceType.py
ext_cloud/Azure/AzureCompute/AzureInstanceTypeDict.py
ext_cloud/Azure/AzureCompute/__init__.py
ext_cloud/Azure/AzureImages/AzureImage.py
ext_cloud/Azure/AzureImages/AzureImages.py
ext_cloud/Azure/AzureImages/__init__.py
ext_cloud/Azure/AzureRegions/AzureRegion.py
