Metadata-Version: 1.0
Name: ext-cloud
Version: 2017.10.18
Summary: Multi cloud library
Home-page: https://github.com/Hawkgirl/ext_cloud/
Author: Hawkgril
Author-email: hawkgirlgit@gmail.com
License: BSD
Platform: UNKNOWN
